tb.v
`define PERIOD 10
module tb();
reg clk ;
reg resetn;
reg up_down;
reg preload;
reg enable;
reg [7:0] data;
wire[7:0] count;

initial 
begin
clk = 0;
forever 
#(`PERIOD/2) clk = ~clk;
end

task waitforclk(input integer n);
repeat(n)
        @(posedge clk);
endtask

counter dut( 
	.clk(clk),
	.resetn(resetn),
	.up_down(up_down),
	.preload(preload),
	.data(data),
	.enable(enable),
	.count(count)
);

initial begin
$dumpfile("tb.vcd");
$dumpvars();
clk=0;
resetn= 0;
data =20;
preload =0 ;
enable =0;

#10 
enable =1;
resetn =0;
up_down =1;
#500 
up_down=0;
#100 
up_down = 1;
#150 
resetn =1;
waitforclk(13);
#500 
preload =1;
data= 8'b00001100;
up_down= 1;
#190 
preload =0 ;
data = 8'h09;
#1000
$finish();

end
endmodule

tb.vcd
$date
	Thu Dec 19 11:54:57 2024
$end
$version
	Icarus Verilog
$end
$timescale
	1ps
$end
$scope module tb $end
$var wire 8 ! count [7:0] $end
$var reg 1 " clk $end
$var reg 8 # data [7:0] $end
$var reg 1 $ enable $end
$var reg 1 % preload $end
$var reg 1 & resetn $end
$var reg 1 ' up_down $end
$scope module dut $end
$var wire 1 " clk $end
$var wire 8 ( data [7:0] $end
$var wire 1 $ enable $end
$var wire 1 % preload $end
$var wire 1 & resetn $end
$var wire 1 ' up_down $end
$var reg 8 ) count [7:0] $end
$upscope $end
$scope task waitforclk $end
$var integer 32 * n [31:0] $end
$upscope $end
$upscope $end
$enddefinitions $end
#0
$dumpvars
bx *
b0 )
b10100 (
x'
0&
0%
0$
b10100 #
0"
b0 !
$end
#5000
1"
#10000
0"
1'
1$
#15000
1"
#20000
0"
#25000
1"
#30000
0"
#35000
1"
#40000
0"
#45000
1"
#50000
0"
#55000
1"
#60000
0"
#65000
1"
#70000
0"
#75000
1"
#80000
0"
#85000
1"
#90000
0"
#95000
1"
#100000
0"
#105000
1"
#110000
0"
#115000
1"
#120000
0"
#125000
1"
#130000
0"
#135000
1"
#140000
0"
#145000
1"
#150000
0"
#155000
1"
#160000
0"
#165000
1"
#170000
0"
#175000
1"
#180000
0"
#185000
1"
#190000
0"
#195000
1"
#200000
0"
#205000
1"
#210000
0"
#215000
1"
#220000
0"
#225000
1"
#230000
0"
#235000
1"
#240000
0"
#245000
1"
#250000
0"
#255000
1"
#260000
0"
#265000
1"
#270000
0"
#275000
1"
#280000
0"
#285000
1"
#290000
0"
#295000
1"
#300000
0"
#305000
1"
#310000
0"
#315000
1"
#320000
0"
#325000
1"
#330000
0"
#335000
1"
#340000
0"
#345000
1"
#350000
0"
#355000
1"
#360000
0"
#365000
1"
#370000
0"
#375000
1"
#380000
0"
#385000
1"
#390000
0"
#395000
1"
#400000
0"
#405000
1"
#410000
0"
#415000
1"
#420000
0"
#425000
1"
#430000
0"
#435000
1"
#440000
0"
#445000
1"
#450000
0"
#455000
1"
#460000
0"
#465000
1"
#470000
0"
#475000
1"
#480000
0"
#485000
1"
#490000
0"
#495000
1"
#500000
0"
#505000
1"
#510000
0"
0'
#515000
1"
#520000
0"
#525000
1"
#530000
0"
#535000
1"
#540000
0"
#545000
1"
#550000
0"
#555000
1"
#560000
0"
#565000
1"
#570000
0"
#575000
1"
#580000
0"
#585000
1"
#590000
0"
#595000
1"
#600000
0"
#605000
1"
#610000
0"
1'
#615000
1"
#620000
0"
#625000
1"
#630000
0"
#635000
1"
#640000
0"
#645000
1"
#650000
0"
#655000
1"
#660000
0"
#665000
1"
#670000
0"
#675000
1"
#680000
0"
#685000
1"
#690000
0"
#695000
1"
#700000
0"
#705000
1"
#710000
0"
#715000
1"
#720000
0"
#725000
1"
#730000
0"
#735000
1"
#740000
0"
#745000
1"
#750000
0"
#755000
1"
#760000
0"
b1101 *
1&
#765000
b1 !
b1 )
1"
#770000
0"
#775000
b10 !
b10 )
1"
#780000
0"
#785000
b11 !
b11 )
1"
#790000
0"
#795000
b100 !
b100 )
1"
#800000
0"
#805000
b101 !
b101 )
1"
#810000
0"
#815000
b110 !
b110 )
1"
#820000
0"
#825000
b111 !
b111 )
1"
#830000
0"
#835000
b1000 !
b1000 )
1"
#840000
0"
#845000
b1001 !
b1001 )
1"
#850000
0"
#855000
b1010 !
b1010 )
1"
#860000
0"
#865000
b1011 !
b1011 )
1"
#870000
0"
#875000
b1100 !
b1100 )
1"
#880000
0"
#885000
b1101 !
b1101 )
1"
#890000
0"
#895000
b1110 !
b1110 )
1"
#900000
0"
#905000
b1111 !
b1111 )
1"
#910000
0"
#915000
b10000 !
b10000 )
1"
#920000
0"
#925000
b10001 !
b10001 )
1"
#930000
0"
#935000
b10010 !
b10010 )
1"
#940000
0"
#945000
b10011 !
b10011 )
1"
#950000
0"
#955000
b10100 !
b10100 )
1"
#960000
0"
#965000
b10101 !
b10101 )
1"
#970000
0"
#975000
b10110 !
b10110 )
1"
#980000
0"
#985000
b10111 !
b10111 )
1"
#990000
0"
#995000
b11000 !
b11000 )
1"
#1000000
0"
#1005000
b11001 !
b11001 )
1"
#1010000
0"
#1015000
b11010 !
b11010 )
1"
#1020000
0"
#1025000
b11011 !
b11011 )
1"
#1030000
0"
#1035000
b11100 !
b11100 )
1"
#1040000
0"
#1045000
b11101 !
b11101 )
1"
#1050000
0"
#1055000
b11110 !
b11110 )
1"
#1060000
0"
#1065000
b11111 !
b11111 )
1"
#1070000
0"
#1075000
b100000 !
b100000 )
1"
#1080000
0"
#1085000
b100001 !
b100001 )
1"
#1090000
0"
#1095000
b100010 !
b100010 )
1"
#1100000
0"
#1105000
b100011 !
b100011 )
1"
#1110000
0"
#1115000
b100100 !
b100100 )
1"
#1120000
0"
#1125000
b100101 !
b100101 )
1"
#1130000
0"
#1135000
b100110 !
b100110 )
1"
#1140000
0"
#1145000
b100111 !
b100111 )
1"
#1150000
0"
#1155000
b101000 !
b101000 )
1"
#1160000
0"
#1165000
b101001 !
b101001 )
1"
#1170000
0"
#1175000
b101010 !
b101010 )
1"
#1180000
0"
#1185000
b101011 !
b101011 )
1"
#1190000
0"
#1195000
b101100 !
b101100 )
1"
#1200000
0"
#1205000
b101101 !
b101101 )
1"
#1210000
0"
#1215000
b101110 !
b101110 )
1"
#1220000
0"
#1225000
b101111 !
b101111 )
1"
#1230000
0"
#1235000
b110000 !
b110000 )
1"
#1240000
0"
#1245000
b110001 !
b110001 )
1"
#1250000
0"
#1255000
b110010 !
b110010 )
1"
#1260000
0"
#1265000
b110011 !
b110011 )
1"
#1270000
0"
#1275000
b110100 !
b110100 )
1"
#1280000
0"
#1285000
b110101 !
b110101 )
1"
#1290000
0"
#1295000
b110110 !
b110110 )
1"
#1300000
0"
#1305000
b110111 !
b110111 )
1"
#1310000
0"
#1315000
b111000 !
b111000 )
1"
#1320000
0"
#1325000
b111001 !
b111001 )
1"
#1330000
0"
#1335000
b111010 !
b111010 )
1"
#1340000
0"
#1345000
b111011 !
b111011 )
1"
#1350000
0"
#1355000
b111100 !
b111100 )
1"
#1360000
0"
#1365000
b111101 !
b111101 )
1"
#1370000
0"
#1375000
b111110 !
b111110 )
1"
#1380000
0"
#1385000
b1100 !
b1100 )
1"
b1100 #
b1100 (
1%
#1390000
0"
#1395000
b1100 !
b1100 )
1"
#1400000
0"
#1405000
b1100 !
b1100 )
1"
#1410000
0"
#1415000
b1100 !
b1100 )
1"
#1420000
0"
#1425000
b1100 !
b1100 )
1"
#1430000
0"
#1435000
b1100 !
b1100 )
1"
#1440000
0"
#1445000
b1100 !
b1100 )
1"
#1450000
0"
#1455000
b1100 !
b1100 )
1"
#1460000
0"
#1465000
b1100 !
b1100 )
1"
#1470000
0"
#1475000
b1100 !
b1100 )
1"
#1480000
0"
#1485000
b1100 !
b1100 )
1"
#1490000
0"
#1495000
b1100 !
b1100 )
1"
#1500000
0"
#1505000
b1100 !
b1100 )
1"
#1510000
0"
#1515000
b1100 !
b1100 )
1"
#1520000
0"
#1525000
b1100 !
b1100 )
1"
#1530000
0"
#1535000
b1100 !
b1100 )
1"
#1540000
0"
#1545000
b1100 !
b1100 )
1"
#1550000
0"
#1555000
b1100 !
b1100 )
1"
#1560000
0"
#1565000
b1100 !
b1100 )
1"
#1570000
0"
#1575000
b1101 !
b1101 )
1"
b1001 #
b1001 (
0%
#1580000
0"
#1585000
b1110 !
b1110 )
1"
#1590000
0"
#1595000
b1111 !
b1111 )
1"
#1600000
0"
#1605000
b10000 !
b10000 )
1"
#1610000
0"
#1615000
b10001 !
b10001 )
1"
#1620000
0"
#1625000
b10010 !
b10010 )
1"
#1630000
0"
#1635000
b10011 !
b10011 )
1"
#1640000
0"
#1645000
b10100 !
b10100 )
1"
#1650000
0"
#1655000
b10101 !
b10101 )
1"
#1660000
0"
#1665000
b10110 !
b10110 )
1"
#1670000
0"
#1675000
b10111 !
b10111 )
1"
#1680000
0"
#1685000
b11000 !
b11000 )
1"
#1690000
0"
#1695000
b11001 !
b11001 )
1"
#1700000
0"
#1705000
b11010 !
b11010 )
1"
#1710000
0"
#1715000
b11011 !
b11011 )
1"
#1720000
0"
#1725000
b11100 !
b11100 )
1"
#1730000
0"
#1735000
b11101 !
b11101 )
1"
#1740000
0"
#1745000
b11110 !
b11110 )
1"
#1750000
0"
#1755000
b11111 !
b11111 )
1"
#1760000
0"
#1765000
b100000 !
b100000 )
1"
#1770000
0"
#1775000
b100001 !
b100001 )
1"
#1780000
0"
#1785000
b100010 !
b100010 )
1"
#1790000
0"
#1795000
b100011 !
b100011 )
1"
#1800000
0"
#1805000
b100100 !
b100100 )
1"
#1810000
0"
#1815000
b100101 !
b100101 )
1"
#1820000
0"
#1825000
b100110 !
b100110 )
1"
#1830000
0"
#1835000
b100111 !
b100111 )
1"
#1840000
0"
#1845000
b101000 !
b101000 )
1"
#1850000
0"
#1855000
b101001 !
b101001 )
1"
#1860000
0"
#1865000
b101010 !
b101010 )
1"
#1870000
0"
#1875000
b101011 !
b101011 )
1"
#1880000
0"
#1885000
b101100 !
b101100 )
1"
#1890000
0"
#1895000
b101101 !
b101101 )
1"
#1900000
0"
#1905000
b101110 !
b101110 )
1"
#1910000
0"
#1915000
b101111 !
b101111 )
1"
#1920000
0"
#1925000
b110000 !
b110000 )
1"
#1930000
0"
#1935000
b110001 !
b110001 )
1"
#1940000
0"
#1945000
b110010 !
b110010 )
1"
#1950000
0"
#1955000
b110011 !
b110011 )
1"
#1960000
0"
#1965000
b110100 !
b110100 )
1"
#1970000
0"
#1975000
b110101 !
b110101 )
1"
#1980000
0"
#1985000
b110110 !
b110110 )
1"
#1990000
0"
#1995000
b110111 !
b110111 )
1"
#2000000
0"
#2005000
b111000 !
b111000 )
1"
#2010000
0"
#2015000
b111001 !
b111001 )
1"
#2020000
0"
#2025000
b111010 !
b111010 )
1"
#2030000
0"
#2035000
b111011 !
b111011 )
1"
#2040000
0"
#2045000
b111100 !
b111100 )
1"
#2050000
0"
#2055000
b111101 !
b111101 )
1"
#2060000
0"
#2065000
b111110 !
b111110 )
1"
#2070000
0"
#2075000
b111111 !
b111111 )
1"
#2080000
0"
#2085000
b1000000 !
b1000000 )
1"
#2090000
0"
#2095000
b1000001 !
b1000001 )
1"
#2100000
0"
#2105000
b1000010 !
b1000010 )
1"
#2110000
0"
#2115000
b1000011 !
b1000011 )
1"
#2120000
0"
#2125000
b1000100 !
b1000100 )
1"
#2130000
0"
#2135000
b1000101 !
b1000101 )
1"
#2140000
0"
#2145000
b1000110 !
b1000110 )
1"
#2150000
0"
#2155000
b1000111 !
b1000111 )
1"
#2160000
0"
#2165000
b1001000 !
b1001000 )
1"
#2170000
0"
#2175000
b1001001 !
b1001001 )
1"
#2180000
0"
#2185000
b1001010 !
b1001010 )
1"
#2190000
0"
#2195000
b1001011 !
b1001011 )
1"
#2200000
0"
#2205000
b1001100 !
b1001100 )
1"
#2210000
0"
#2215000
b1001101 !
b1001101 )
1"
#2220000
0"
#2225000
b1001110 !
b1001110 )
1"
#2230000
0"
#2235000
b1001111 !
b1001111 )
1"
#2240000
0"
#2245000
b1010000 !
b1010000 )
1"
#2250000
0"
#2255000
b1010001 !
b1010001 )
1"
#2260000
0"
#2265000
b1010010 !
b1010010 )
1"
#2270000
0"
#2275000
b1010011 !
b1010011 )
1"
#2280000
0"
#2285000
b1010100 !
b1010100 )
1"
#2290000
0"
#2295000
b1010101 !
b1010101 )
1"
#2300000
0"
#2305000
b1010110 !
b1010110 )
1"
#2310000
0"
#2315000
b1010111 !
b1010111 )
1"
#2320000
0"
#2325000
b1011000 !
b1011000 )
1"
#2330000
0"
#2335000
b1011001 !
b1011001 )
1"
#2340000
0"
#2345000
b1011010 !
b1011010 )
1"
#2350000
0"
#2355000
b1011011 !
b1011011 )
1"
#2360000
0"
#2365000
b1011100 !
b1011100 )
1"
#2370000
0"
#2375000
b1011101 !
b1011101 )
1"
#2380000
0"
#2385000
b1011110 !
b1011110 )
1"
#2390000
0"
#2395000
b1011111 !
b1011111 )
1"
#2400000
0"
#2405000
b1100000 !
b1100000 )
1"
#2410000
0"
#2415000
b1100001 !
b1100001 )
1"
#2420000
0"
#2425000
b1100010 !
b1100010 )
1"
#2430000
0"
#2435000
b1100011 !
b1100011 )
1"
#2440000
0"
#2445000
b1100100 !
b1100100 )
1"
#2450000
0"
#2455000
b1100101 !
b1100101 )
1"
#2460000
0"
#2465000
b1100110 !
b1100110 )
1"
#2470000
0"
#2475000
b1100111 !
b1100111 )
1"
#2480000
0"
#2485000
b1101000 !
b1101000 )
1"
#2490000
0"
#2495000
b1101001 !
b1101001 )
1"
#2500000
0"
#2505000
b1101010 !
b1101010 )
1"
#2510000
0"
#2515000
b1101011 !
b1101011 )
1"
#2520000
0"
#2525000
b1101100 !
b1101100 )
1"
#2530000
0"
#2535000
b1101101 !
b1101101 )
1"
#2540000
0"
#2545000
b1101110 !
b1101110 )
1"
#2550000
0"
#2555000
b1101111 !
b1101111 )
1"
#2560000
0"
#2565000
b1110000 !
b1110000 )
1"
#2570000
0"
#2575000
b1110001 !
b1110001 )
1"
